microcosm_flask/__init__.py
microcosm_flask/audit.py
microcosm_flask/basic_auth.py
microcosm_flask/cloning.py
microcosm_flask/context.py
microcosm_flask/converters.py
microcosm_flask/enums.py
microcosm_flask/errors.py
microcosm_flask/factories.py
microcosm_flask/forwarding.py
microcosm_flask/linking.py
microcosm_flask/matchers.py
microcosm_flask/memory.py
microcosm_flask/metrics.py
microcosm_flask/metrics_classifier.py
microcosm_flask/namespaces.py
microcosm_flask/naming.py
microcosm_flask/operations.py
microcosm_flask/paging.py
microcosm_flask/paths.py
microcosm_flask/profiling.py
microcosm_flask/routing.py
microcosm_flask/runserver.py
microcosm_flask/sentry.py
microcosm_flask/session.py
microcosm_flask/conventions/__init__.py
microcosm_flask/conventions/alias.py
microcosm_flask/conventions/base.py
microcosm_flask/conventions/build_info.py
microcosm_flask/conventions/catchall.py
microcosm_flask/conventions/config.py
microcosm_flask/conventions/crud.py
microcosm_flask/conventions/crud_adapter.py
microcosm_flask/conventions/discovery.py
microcosm_flask/conventions/encoding.py
microcosm_flask/conventions/health.py
microcosm_flask/conventions/landing.py
microcosm_flask/conventions/logging_level.py
microcosm_flask/conventions/registry.py
microcosm_flask/conventions/relation.py
microcosm_flask/conventions/saved_search.py
microcosm_flask/conventions/swagger.py
microcosm_flask/conventions/upload.py
microcosm_flask/decorators/__init__.py
microcosm_flask/decorators/logging.py
microcosm_flask/decorators/schemas.py
microcosm_flask/encryption/__init__.py
microcosm_flask/encryption/conventions/__init__.py
microcosm_flask/encryption/conventions/crud_adapter.py
microcosm_flask/fields/__init__.py
microcosm_flask/fields/cleaned_field.py
microcosm_flask/fields/enum_field.py
microcosm_flask/fields/language_field.py
microcosm_flask/fields/order_by_field.py
microcosm_flask/fields/query_string_list.py
microcosm_flask/fields/timestamp_field.py
microcosm_flask/fields/uri_field.py
microcosm_flask-6.1.0.dist-info/LICENSE
microcosm_flask-6.1.0.dist-info/METADATA
microcosm_flask-6.1.0.dist-info/WHEEL
microcosm_flask-6.1.0.dist-info/entry_points.txt
microcosm_flask-6.1.0.dist-info/top_level.txt
microcosm_flask-6.1.0.dist-info/RECORD
